fansauth/__init__.py
fansauth/cons.py
fansauth/lib/__init__.py
fansauth/lib/auth.py
fansauth/server/__init__.py
fansauth/server/__main__.py
fansauth/server/app.py
fansauth/server/app_test.py
fansauth/server/db.py
fansauth/server/deps.py
fansauth/server/env.py
fansauth/server/env_test.py
fansauth/server/user.py
fansauth/server/utils.py
fansauth-0.1.9.dist-info/METADATA
fansauth-0.1.9.dist-info/WHEEL
fansauth-0.1.9.dist-info/top_level.txt
fansauth-0.1.9.dist-info/RECORD
