Metadata-Version: 2.4
Name: fansauth
Version: 0.1.9
Summary: fans656's authorization helper
Requires-Python: >=3.9
Requires-Dist: cryptography>=44.0.2
Requires-Dist: duf>=0.0.14
Requires-Dist: peewee>=3.17.9
Requires-Dist: pyjwt>=2.10.1
